p3eFritzBox/__init__.py
p3eFritzBox/collector/__init__.py
p3eFritzBox/collector/smarthome.py
p3exporter_fritzbox_smarthome-1.1.0.dist-info/LICENSE
p3exporter_fritzbox_smarthome-1.1.0.dist-info/METADATA
p3exporter_fritzbox_smarthome-1.1.0.dist-info/WHEEL
p3exporter_fritzbox_smarthome-1.1.0.dist-info/top_level.txt
p3exporter_fritzbox_smarthome-1.1.0.dist-info/RECORD
