Metadata-Version: 2.1
Name: p3exporter-fritzbox-smarthome
Version: 1.1.0
Summary: Fritz!Box p3exporter collector module
Home-page: http://codeaffen.org/projects/p3efritzbox
Author: Christian Meißner
Author-email: cme@codeaffen.org
License: GPLv3
Classifier: License :: OSI Approved :: GNU General Public License v3 (GPLv3)
Classifier: Programming Language :: Python :: 3
Classifier: Programming Language :: Python :: 3.6
Classifier: Programming Language :: Python :: 3.7
Classifier: Programming Language :: Python :: 3.8
Classifier: Programming Language :: Python :: 3.9
Classifier: Programming Language :: Python :: 3.10
License-File: LICENSE
Requires-Dist: pyfritzhome
Requires-Dist: p3exporter (>=1.2.0)
